BS
QS
