Metadata-Version: 1.0
Name: pyBS-QS
Version: 0.17
Summary: this package has been prepared a binarysearch allgorithm using quicksort
Home-page: UNKNOWN
Author: UNKNOWN
Author-email: UNKNOWN
License: UNKNOWN
Platform: UNKNOWN
